mo_json_config/__init__.py
mo_json_config/configuration.py
mo_json_config/convert.py
mo_json_config/expand_locals.py
mo_json_config/expander.py
mo_json_config/mocks.py
mo_json_config/schemes.py
mo_json_config/ssm.py
mo_json_config-5.693.25169.dist-info/licenses/LICENSE.txt
mo_json_config-5.693.25169.dist-info/METADATA
mo_json_config-5.693.25169.dist-info/WHEEL
mo_json_config-5.693.25169.dist-info/top_level.txt
mo_json_config-5.693.25169.dist-info/RECORD
