Metadata-Version: 2.4
Name: mo-json-config
Version: 5.693.25169
Summary: More JSON Configuration! JSON configuration files with `$ref` and template overlays
Home-page: https://github.com/klahnakoski/mo-json-config
Author: Kyle Lahnakoski
Author-email: kyle@lahnakoski.com
License: MPL 2.0
Classifier: Development Status :: 4 - Beta
Classifier: Topic :: Software Development :: Libraries
Classifier: Topic :: Software Development :: Libraries :: Python Modules
Classifier: Programming Language :: Python :: 3.8
Classifier: Programming Language :: Python :: 3.9
Classifier: Programming Language :: Python :: 3.10
Classifier: License :: OSI Approved :: Mozilla Public License 2.0 (MPL 2.0)
Classifier: Programming Language :: Python :: 3.11
Classifier: Programming Language :: Python :: 3.12
Classifier: Programming Language :: Python :: 3.13
License-File: LICENSE.txt
Requires-Dist: hjson
Requires-Dist: mo-dots==10.685.25166
Requires-Dist: mo-files==6.690.25168
Requires-Dist: mo-future==7.685.25166
Requires-Dist: mo-json==6.686.25166
Requires-Dist: mo-logs==8.685.25166
Requires-Dist: requests
Provides-Extra: tests
Requires-Dist: mo-testing; extra == "tests"
Requires-Dist: keyring; extra == "tests"
Requires-Dist: boto3; extra == "tests"
Requires-Dist: pyyaml; extra == "tests"
Requires-Dist: moto; extra == "tests"
Dynamic: author
Dynamic: author-email
Dynamic: classifier
Dynamic: description
Dynamic: description-content-type
Dynamic: home-page
Dynamic: license
Dynamic: license-file
Dynamic: provides-extra
Dynamic: requires-dist
Dynamic: summary
